extractor/__init__.py
extractor/base.py
extractor/eda_feature.py
extractor/export_feature.py
extractor/loader_feature.py
extractor/unique_val_feature.py
edabyalex-0.1.2.dist-info/METADATA
edabyalex-0.1.2.dist-info/WHEEL
edabyalex-0.1.2.dist-info/licenses/LICENSE.txt
edabyalex-0.1.2.dist-info/RECORD
