Metadata-Version: 2.4
Name: edabyalex
Version: 0.1.2
Summary: A Python package for streamlined Exploratory Data Analysis (EDA) and Extraction Transform Load (ETL)
Project-URL: Homepage, https://github.com/alexyang790/EDAbyAlex
Author-email: Alex Yang <zy7ts@virginia.edu>
License-Expression: MIT
License-File: LICENSE.txt
Classifier: Development Status :: 3 - Alpha
Classifier: Intended Audience :: Developers
Classifier: Intended Audience :: Science/Research
Classifier: License :: OSI Approved :: MIT License
Classifier: Programming Language :: Python :: 3
Requires-Python: >=3.7
Requires-Dist: glob2>=0.7
Requires-Dist: numpy>=1.18.0
Requires-Dist: openpyxl>=3.0.0
Requires-Dist: pandas>=1.0.0
